[
  {
    "degree": "school",
    "title": "Primary and Middle School",
    "institution": "Maharashtra Education Society, Baramati",
    "location": "Baramati, Maharashtra, India",
    "start_date": "2008-06-01",
    "end_date": "2017-05-01",
    "currently_studying": false,
    "description": "Completed foundational schooling from LKG to 7th standard with active participation in academics and co-curricular activities.",
    "grade": "",
    "courses": ["Mathematics", "Science", "English", "Social Studies", "Computer Basics"],
    "achievements": [],
    "logo": "",
    "certificate": "",
    "featured": false,
    "display_order": 1,
    "is_active": true
  },
  {
    "degree": "school",
    "title": "8th Standard",
    "institution": "Radha Shyam N. Aggrawal School and Junior College",
    "location": "Baramati, Maharashtra, India",
    "start_date": "2017-06-01",
    "end_date": "2018-05-01",
    "currently_studying": false,
    "description": "Completed 8th standard before moving to a JEE-focused academic track.",
    "grade": "",
    "courses": ["Mathematics", "Science", "English", "Social Studies", "Computer Science"],
    "achievements": [],
    "logo": "",
    "certificate": "",
    "featured": false,
    "display_order": 2,
    "is_active": true
  },
  {
    "degree": "high_school",
    "title": "High School and Junior College - JEE Preparation Track",
    "institution": "Chaitanya International School and Academy",
    "location": "Baramati, Maharashtra, India",
    "start_date": "2018-06-01",
    "end_date": "2023-05-01",
    "currently_studying": false,
    "description": "Completed 9th to 12th with integrated JEE and CET preparation, building a strong foundation in physics, chemistry, and mathematics.",
    "grade": "10th: 92%, 12th: 76%",
    "courses": ["Physics", "Chemistry", "Mathematics", "English", "JEE Mains Coaching", "MHT-CET Preparation"],
    "achievements": ["MHT-CET: 96 Percentile", "JEE Mains: 78 Percentile"],
    "logo": "",
    "certificate": "",
    "featured": true,
    "display_order": 3,
    "is_active": true
  },
  {
    "degree": "bachelor",
    "title": "Bachelor of Technology in Computer Science",
    "institution": "Rajashree Shahu College of Engineering (JSPM Tathawade)",
    "location": "Pune, Maharashtra, India",
    "start_date": "2023-08-01",
    "end_date": null,
    "currently_studying": true,
    "description": "Pursuing B.Tech in Computer Science with focus on core CS subjects, machine learning, and software development.",
    "grade": "CGPA: 9.43 (ongoing)",
    "courses": ["Data Structures", "Algorithms", "DBMS", "Machine Learning", "AI", "Operating Systems", "Python", "C++", "Web Development"],
    "achievements": ["CGPA: 9.43 (ongoing)"],
    "logo": "",
    "certificate": "",
    "featured": true,
    "display_order": 4,
    "is_active": true
  },
  {
    "degree": "online",
    "title": "Machine Learning Specialization",
    "institution": "Coursera - Andrew Ng",
    "location": "Online",
    "start_date": "2024-01-01",
    "end_date": null,
    "currently_studying": true,
    "description": "Coursework covering supervised learning, unsupervised learning, neural networks, and model evaluation.",
    "grade": "Completed with strong performance",
    "courses": ["Supervised Learning", "Unsupervised Learning", "Neural Networks", "TensorFlow", "Model Evaluation"],
    "achievements": ["Completed with strong performance"],
    "logo": "",
    "certificate": "",
    "featured": false,
    "display_order": 5,
    "is_active": true
  }
]

